doc/conf.py
tests/_gen_figures/__init__.py
tests/_gen_figures/gen_doc_examples.py
yayaml/__init__.py
yayaml/constructors.py
yayaml/exceptions.py
yayaml/io.py
yayaml/py.typed
yayaml/representers.py
yayaml/tools.py
yayaml/yaml.py
yayaml-0.3.0.dist-info/licenses/LICENSE
yayaml-0.3.0.dist-info/METADATA
yayaml-0.3.0.dist-info/WHEEL
yayaml-0.3.0.dist-info/top_level.txt
yayaml-0.3.0.dist-info/RECORD
