Metadata-Version: 2.4
Name: yayaml
Version: 0.3.0
Summary: yayaml makes yaml nicer. yay!
Author-email: Yunus Sevinchan <blsqr@posteo.com>
License: BSD-2-Clause
Project-URL: Homepage, https://gitlab.com/blsqr/yayaml
Project-URL: Documentation, https://yayaml.readthedocs.io
Project-URL: Repository, https://gitlab.com/blsqr/yayaml
Project-URL: Changelog, https://gitlab.com/blsqr/yayaml/-/blob/main/CHANGELOG.md
Classifier: License :: OSI Approved :: BSD License
Classifier: Programming Language :: Python :: 3.8
Classifier: Programming Language :: Python :: 3.9
Classifier: Programming Language :: Python :: 3.10
Classifier: Programming Language :: Python :: 3.11
Classifier: Programming Language :: Python :: 3.12
Classifier: Programming Language :: Python :: 3.13
Classifier: Programming Language :: Python :: 3.14
Classifier: Development Status :: 5 - Production/Stable
Classifier: Topic :: Utilities
Requires-Python: >=3.8
License-File: LICENSE
Requires-Dist: numpy
Requires-Dist: ruamel.yaml
Provides-Extra: test
Requires-Dist: pytest; extra == "test"
Requires-Dist: pytest-cov; extra == "test"
Requires-Dist: pre-commit; extra == "test"
Provides-Extra: doc
Requires-Dist: sphinx>=5.3; extra == "doc"
Requires-Dist: sphinx-book-theme; extra == "doc"
Requires-Dist: sphinx-togglebutton; extra == "doc"
Requires-Dist: ipython>=7.0; extra == "doc"
Requires-Dist: myst-parser[linkify]; extra == "doc"
Requires-Dist: pytest; extra == "doc"
Provides-Extra: dev
Requires-Dist: yayaml[doc,test]; extra == "dev"
Dynamic: license-file
